<data><row DIC_CODE="510101" DIC_TEXT="市辖区" DIC_SPELL="sxq" DIC_ASPELL="shixiaqu"/><row DIC_CODE="510104" DIC_TEXT="锦江区" DIC_SPELL="jjq" DIC_ASPELL="jinjiangqu"/><row DIC_CODE="510105" DIC_TEXT="青羊区" DIC_SPELL="qyq" DIC_ASPELL="qingyangqu"/><row DIC_CODE="510106" DIC_TEXT="金牛区" DIC_SPELL="jnq" DIC_ASPELL="jinniuqu"/><row DIC_CODE="510107" DIC_TEXT="武侯区" DIC_SPELL="whq" DIC_ASPELL="wuhouqu"/><row DIC_CODE="510108" DIC_TEXT="成华区" DIC_SPELL="chq" DIC_ASPELL="chenghuaqu"/><row DIC_CODE="510112" DIC_TEXT="龙泉驿区" DIC_SPELL="lqyq" DIC_ASPELL="longquanyiqu"/><row DIC_CODE="510113" DIC_TEXT="青白江区" DIC_SPELL="qbjq" DIC_ASPELL="qingbaijiangqu"/><row DIC_CODE="510114" DIC_TEXT="新都区" DIC_SPELL="xdq" DIC_ASPELL="xindouqu"/><row DIC_CODE="510115" DIC_TEXT="温江区" DIC_SPELL="wjq" DIC_ASPELL="wenjiangqu"/><row DIC_CODE="510121" DIC_TEXT="金堂县" DIC_SPELL="jtx" DIC_ASPELL="jintangxian"/><row DIC_CODE="510122" DIC_TEXT="双流县" DIC_SPELL="slx" DIC_ASPELL="shuangliuxian"/><row DIC_CODE="510124" DIC_TEXT="郫县" DIC_SPELL="px" DIC_ASPELL="pixian"/><row DIC_CODE="510129" DIC_TEXT="大邑县" DIC_SPELL="dyx" DIC_ASPELL="dayixian"/><row DIC_CODE="510131" DIC_TEXT="蒲江县" DIC_SPELL="pjx" DIC_ASPELL="pujiangxian"/><row DIC_CODE="510132" DIC_TEXT="新津县" DIC_SPELL="xjx" DIC_ASPELL="xinjinxian"/><row DIC_CODE="510181" DIC_TEXT="都江堰市" DIC_SPELL="djys" DIC_ASPELL="doujiangyanshi"/><row DIC_CODE="510182" DIC_TEXT="彭州市" DIC_SPELL="pzs" DIC_ASPELL="pengzhoushi"/><row DIC_CODE="510183" DIC_TEXT="邛崃市" DIC_SPELL="qls" DIC_ASPELL="qionglaishi"/><row DIC_CODE="510184" DIC_TEXT="崇州市" DIC_SPELL="czs" DIC_ASPELL="chongzhoushi"/></data>
