<data><row DIC_CODE="610401" DIC_TEXT="市辖区" DIC_SPELL="sxq" DIC_ASPELL="shixiaqu"/><row DIC_CODE="610402" DIC_TEXT="秦都区" DIC_SPELL="qdq" DIC_ASPELL="qindouqu"/><row DIC_CODE="610403" DIC_TEXT="杨凌区" DIC_SPELL="ylq" DIC_ASPELL="yanglingqu"/><row DIC_CODE="610404" DIC_TEXT="渭城区" DIC_SPELL="wcq" DIC_ASPELL="weichengqu"/><row DIC_CODE="610422" DIC_TEXT="三原县" DIC_SPELL="syx" DIC_ASPELL="sanyuanxian"/><row DIC_CODE="610423" DIC_TEXT="泾阳县" DIC_SPELL="jyx" DIC_ASPELL="jingyangxian"/><row DIC_CODE="610424" DIC_TEXT="乾县" DIC_SPELL="gx" DIC_ASPELL="ganxian"/><row DIC_CODE="610425" DIC_TEXT="礼泉县" DIC_SPELL="lqx" DIC_ASPELL="liquanxian"/><row DIC_CODE="610426" DIC_TEXT="永寿县" DIC_SPELL="ysx" DIC_ASPELL="yongshouxian"/><row DIC_CODE="610427" DIC_TEXT="彬县" DIC_SPELL="bx" DIC_ASPELL="binxian"/><row DIC_CODE="610428" DIC_TEXT="长武县" DIC_SPELL="cwx" DIC_ASPELL="changwuxian"/><row DIC_CODE="610429" DIC_TEXT="旬邑县" DIC_SPELL="xyx" DIC_ASPELL="xunyixian"/><row DIC_CODE="610430" DIC_TEXT="淳化县" DIC_SPELL="zhx" DIC_ASPELL="zhunhuaxian"/><row DIC_CODE="610431" DIC_TEXT="武功县" DIC_SPELL="wgx" DIC_ASPELL="wugongxian"/><row DIC_CODE="610481" DIC_TEXT="兴平市" DIC_SPELL="xps" DIC_ASPELL="xingpingshi"/></data>
