<data><row DIC_CODE="610100" DIC_TEXT="西安市" DIC_SPELL="xas" DIC_ASPELL="xianshi"/><row DIC_CODE="610200" DIC_TEXT="铜川市" DIC_SPELL="tcs" DIC_ASPELL="tongchuanshi"/><row DIC_CODE="610300" DIC_TEXT="宝鸡市" DIC_SPELL="bjs" DIC_ASPELL="baojishi"/><row DIC_CODE="610400" DIC_TEXT="咸阳市" DIC_SPELL="xys" DIC_ASPELL="xianyangshi"/><row DIC_CODE="610500" DIC_TEXT="渭南市" DIC_SPELL="wns" DIC_ASPELL="weinanshi"/><row DIC_CODE="610600" DIC_TEXT="延安市" DIC_SPELL="yas" DIC_ASPELL="yananshi"/><row DIC_CODE="610700" DIC_TEXT="汉中市" DIC_SPELL="hzs" DIC_ASPELL="hanzhongshi"/><row DIC_CODE="610800" DIC_TEXT="榆林市" DIC_SPELL="yls" DIC_ASPELL="yulinshi"/><row DIC_CODE="610900" DIC_TEXT="安康市" DIC_SPELL="aks" DIC_ASPELL="ankangshi"/><row DIC_CODE="611000" DIC_TEXT="商洛市" DIC_SPELL="sls" DIC_ASPELL="shangluoshi"/></data>
